ride_duration/VERSION
ride_duration/__init__.py
ride_duration/predict.py
ride_duration/utils.py
ride_duration_prediction_sunxi1010-0.3.0.dist-info/METADATA
ride_duration_prediction_sunxi1010-0.3.0.dist-info/WHEEL
ride_duration_prediction_sunxi1010-0.3.0.dist-info/top_level.txt
ride_duration_prediction_sunxi1010-0.3.0.dist-info/RECORD
