Metadata-Version: 2.1
Name: ride-duration-prediction-sunxi1010
Version: 0.3.0
Summary: Predicting ride duration for TLC Trip Record Data.
Home-page: https://particle1331.github.io/inefficient-networks/notebooks/mlops/04-deployment/notes.html
Author: Ron Medina
Author-email: particle1331@gmail.com
License: MIT
Classifier: License :: OSI Approved :: MIT License
Classifier: Programming Language :: Python :: 3.9
Requires-Python: >=3.9.0,<3.10
Requires-Dist: scikit-learn (==1.1.2)
Requires-Dist: mlflow (==1.28.0)
Requires-Dist: pandas (<1.5.0,>=1.4.3)
Requires-Dist: joblib (<1.2.0,>=1.1.0)
